odoo/addons/web_chatter_position/README.rst
odoo/addons/web_chatter_position/__init__.py
odoo/addons/web_chatter_position/__manifest__.py
odoo/addons/web_chatter_position/i18n/ca.po
odoo/addons/web_chatter_position/i18n/de.po
odoo/addons/web_chatter_position/i18n/es.po
odoo/addons/web_chatter_position/i18n/fr.po
odoo/addons/web_chatter_position/i18n/fr_BE.po
odoo/addons/web_chatter_position/i18n/hr.po
odoo/addons/web_chatter_position/i18n/it.po
odoo/addons/web_chatter_position/i18n/nl.po
odoo/addons/web_chatter_position/i18n/pt_BR.po
odoo/addons/web_chatter_position/i18n/tr.po
odoo/addons/web_chatter_position/i18n/web_chatter_position.pot
odoo/addons/web_chatter_position/models/__init__.py
odoo/addons/web_chatter_position/models/res_users.py
odoo/addons/web_chatter_position/readme/CONTRIBUTORS.md
odoo/addons/web_chatter_position/readme/DESCRIPTION.md
odoo/addons/web_chatter_position/readme/USAGE.md
odoo/addons/web_chatter_position/static/description/icon.png
odoo/addons/web_chatter_position/static/description/index.html
odoo/addons/web_chatter_position/static/src/js/web_chatter_position.esm.js
odoo/addons/web_chatter_position/static/src/scss/form_controller.scss
odoo/addons/web_chatter_position/static/src/scss/form_renderer.scss
odoo/addons/web_chatter_position/static/src/scss/form_statusbar.scss
odoo/addons/web_chatter_position/views/res_users.xml
odoo/addons/web_chatter_position/views/web.xml
odoo_addon_web_chatter_position-18.0.1.0.1.4.dist-info/METADATA
odoo_addon_web_chatter_position-18.0.1.0.1.4.dist-info/WHEEL
odoo_addon_web_chatter_position-18.0.1.0.1.4.dist-info/top_level.txt
odoo_addon_web_chatter_position-18.0.1.0.1.4.dist-info/RECORD
