Metadata-Version: 2.1
Name: odoo-addon-web_chatter_position
Version: 18.0.1.0.1.4
Requires-Python: >=3.10
Requires-Dist: odoo==18.0.*
Summary: Add an option to change the chatter position
Home-page: https://github.com/OCA/web
License: LGPL-3
Author: Hynsys Technologies, Camptocamp, Alitec Pte Ltd, Odoo Community Association (OCA)
Author-email: support@odoo-community.org
Classifier: Programming Language :: Python
Classifier: Framework :: Odoo
Classifier: Framework :: Odoo :: 18.0
Classifier: License :: OSI Approved :: GNU Lesser General Public License v3 (LGPLv3)
